odoo/addons/sale_loyalty_partner_applicability/README.rst
odoo/addons/sale_loyalty_partner_applicability/__init__.py
odoo/addons/sale_loyalty_partner_applicability/__manifest__.py
odoo/addons/sale_loyalty_partner_applicability/i18n/it.po
odoo/addons/sale_loyalty_partner_applicability/i18n/sale_loyalty_partner_applicability.pot
odoo/addons/sale_loyalty_partner_applicability/models/__init__.py
odoo/addons/sale_loyalty_partner_applicability/models/loyalty_program.py
odoo/addons/sale_loyalty_partner_applicability/models/sale_order.py
odoo/addons/sale_loyalty_partner_applicability/readme/CONFIGURE.md
odoo/addons/sale_loyalty_partner_applicability/readme/CONTRIBUTORS.md
odoo/addons/sale_loyalty_partner_applicability/readme/DESCRIPTION.md
odoo/addons/sale_loyalty_partner_applicability/readme/USAGE.md
odoo/addons/sale_loyalty_partner_applicability/static/description/icon.png
odoo/addons/sale_loyalty_partner_applicability/static/description/index.html
odoo/addons/sale_loyalty_partner_applicability/tests/__init__.py
odoo/addons/sale_loyalty_partner_applicability/tests/test_sale_loyalty_partner_applicability.py
odoo/addons/sale_loyalty_partner_applicability/views/res_config_settings.xml
odoo_addon_sale_loyalty_partner_applicability-18.0.1.0.0.2.dist-info/METADATA
odoo_addon_sale_loyalty_partner_applicability-18.0.1.0.0.2.dist-info/WHEEL
odoo_addon_sale_loyalty_partner_applicability-18.0.1.0.0.2.dist-info/top_level.txt
odoo_addon_sale_loyalty_partner_applicability-18.0.1.0.0.2.dist-info/RECORD
